code_insight/__init__.py
code_insight/core.py
code_insight/multi_analysis.py
code_insight/py.typed
code_insight/code_analysis/__init__.py
code_insight/code_analysis/abstract.py
code_insight/code_analysis/algorithm.py
code_insight/code_analysis/complexity.py
code_insight/code_analysis/quality.py
code_insight/code_analysis/readability.py
code_insight/code_analysis/redundancy.py
code_insight/code_analysis/security.py
code_insight/code_analysis/struct.py
code_insight/code_analysis/style.py
code_insight/trend_analysis/__init__.py
code_insight/trend_analysis/trend_analysis.py
codinsight-0.3.0.dist-info/METADATA
codinsight-0.3.0.dist-info/WHEEL
codinsight-0.3.0.dist-info/top_level.txt
codinsight-0.3.0.dist-info/RECORD
