Metadata-Version: 2.4
Name: codinsight
Version: 0.3.0
Summary: Add your description here
Requires-Python: >=3.12
Requires-Dist: matplotlib>=3.10.5
Requires-Dist: pandas>=2.3.1
Requires-Dist: pycodestyle>=2.14.0
Requires-Dist: pydantic>=2.11.7
Requires-Dist: pydocstyle>=6.3.0
Requires-Dist: pytest>=8.4.1
Requires-Dist: pytest-cov>=6.2.1
Requires-Dist: radon>=6.0.1
Requires-Dist: reportlab>=4.4.3
Requires-Dist: scikit-learn>=1.7.1
